docker_tagging/__init__.py
docker_tagging/__main__.py
docker_tagging/create_manifests.py
docker_tagging/create_version.py
docker_tagging/docker_runner.py
docker_tagging/get_taggers_and_manifests.py
docker_tagging/git_helper.py
docker_tagging/github_set_env.py
docker_tagging/images_hierarchy.py
docker_tagging/manifests.py
docker_tagging/tag_image.py
docker_tagging/taggers.py
docker_tagging-0.12.1.dist-info/entry_points.txt
docker_tagging-0.12.1.dist-info/LICENSE.md
docker_tagging-0.12.1.dist-info/WHEEL
docker_tagging-0.12.1.dist-info/METADATA
docker_tagging-0.12.1.dist-info/RECORD
