Metadata-Version: 2.1
Name: docker-tagging
Version: 0.12.1
Summary: Docker stacks tagging and manifest creation. This project is inspired on https://github.com/jupyter/docker-stacks.
Home-page: https://gitlab.com/weissmedia/docker-tagging.git
License: BSD-3-Clause
Author: Mathias Weiß
Author-email: mail@weissmedia.de
Requires-Python: >=3.8
Classifier: Development Status :: 5 - Production/Stable
Classifier: License :: OSI Approved :: BSD License
Classifier: Natural Language :: English
Classifier: Programming Language :: Python :: 3
Classifier: Programming Language :: Python :: 3.10
Classifier: Programming Language :: Python :: 3.8
Classifier: Programming Language :: Python :: 3.9
Classifier: Topic :: Software Development :: Libraries :: Python Modules
Requires-Dist: PyYAML (>=5.4.1,<6.0.0)
Requires-Dist: docker (>=5.0.3,<6.0.0)
Requires-Dist: plumbum (>=1.7.0,<2.0.0)
Project-URL: Repository, https://gitlab.com/weissmedia/docker-tagging.git
